Metadata-Version: 2.1
Name: dos-image-processing
Version: 0.0.1
Summary: Image Processing Package using skimage - Author = Karina Tiemi Kato
Home-page: https://github.com/kalangosecojf/dio-image-processing-package
Author: Danilo Santos
License: UNKNOWN
Platform: UNKNOWN
Requires-Python: >=3.8
Requires-Dist: matplotlib
Requires-Dist: numpy
Requires-Dist: scikit-image (>=0.16.1)
